{"filter":false,"title":"production.json","tooltip":"/api/config/production.json","undoManager":{"mark":0,"position":0,"stack":[[{"group":"doc","deltas":[{"start":{"row":21,"column":5},"end":{"row":26,"column":5},"action":"insert","lines":[",","    \"facebook\"  : {","        \"app_id\"            : \"1420260414938222\",","        \"secret_key\"        : \"e0a6b89aea7a01cf3ffb1d55c97aee8f\",","        \"verification_token\": \"lgverifytoken\"","    }"]}]}]]},"ace":{"folds":[],"scrolltop":0,"scrollleft":0,"selection":{"start":{"row":26,"column":5},"end":{"row":26,"column":5},"isBackwards":false},"options":{"guessTabSize":true,"useWrapMode":false,"wrapToView":true},"firstLineState":0},"timestamp":1424726875193,"hash":"9ec53a85b18db74a2e9f6fbd53c654f3d4f18ecb"}